{
  "reviewDate": "2026-07-06",
  "generatedAt": "2026-07-06T22:36:01.705165+00:00",
  "modelName": "timesfm",
  "marketRegime": "selective upside bias",
  "analystDecision": "Press the best longs, but keep entries disciplined.",
  "riskPosture": "Risk is not gone. Respect the trim list and do not turn watchlist names into forced trades.",
  "operatorSummary": "The board reads selective upside bias, with 3 buy setups and 2 risk-reduction names. Current evaluation history shows 100.0% 1D hit rate, so the edge looks real but still young.",
  "nextSessionPlan": "Open with AMD, VRT, ANET on the main board, keep SPCX, ORCL marked for risk control, and let weaker holds prove themselves before touching them.",
  "publishSummary": "Fresh generated artifacts are ready for GitHub commit and Vercel rebuild.",
  "forecastCount": 11,
  "buyCount": 3,
  "sellCount": 2,
  "holdCount": 6,
  "bullishCount": 6,
  "bearishCount": 3,
  "averagePredictedReturn": 0.000522,
  "averageOneDayHitRate": 1.0,
  "topLongs": [
    {
      "ticker": "AMD",
      "portfolioAction": "BUY",
      "setupLabel": "Fresh long setup",
      "predictedReturn": 0.010625,
      "basePredictedReturn": 0.010625,
      "adjustedPredictedReturn": 0.010625,
      "calibrationEnabled": false,
      "calibrationModelVersion": null,
      "calibrationStatus": "disabled",
      "calibrationReasons": [],
      "eventRisk": "low",
      "confidenceLabel": "high",
      "trendBias": "Uptrend",
      "convictionScore": 35,
      "currentClose": 552.05,
      "entryPriceTarget": 550.0,
      "targetClose": 557.9469,
      "oneDayHitRate": 1.0,
      "oneDayMae": 0.0006599074796747964,
      "notes": "Bullish forecast with no current position. Plan an entry only if the next session confirms the move and keeps risk tight."
    },
    {
      "ticker": "VRT",
      "portfolioAction": "BUY",
      "setupLabel": "Fresh long setup",
      "predictedReturn": 0.004385,
      "basePredictedReturn": 0.004385,
      "adjustedPredictedReturn": 0.004385,
      "calibrationEnabled": false,
      "calibrationModelVersion": null,
      "calibrationStatus": "disabled",
      "calibrationReasons": [],
      "eventRisk": "moderate",
      "confidenceLabel": "medium",
      "trendBias": "Uptrend",
      "convictionScore": 35,
      "currentClose": 318.47,
      "entryPriceTarget": 317.98,
      "targetClose": 319.8695,
      "oneDayHitRate": 1.0,
      "oneDayMae": 0.0006599074796747964,
      "notes": "Bullish forecast with no current position. Plan an entry only if the next session confirms the move and keeps risk tight."
    },
    {
      "ticker": "ANET",
      "portfolioAction": "BUY",
      "setupLabel": "Fresh long setup",
      "predictedReturn": 0.002245,
      "basePredictedReturn": 0.002245,
      "adjustedPredictedReturn": 0.002245,
      "calibrationEnabled": false,
      "calibrationModelVersion": null,
      "calibrationStatus": "disabled",
      "calibrationReasons": [],
      "eventRisk": "moderate",
      "confidenceLabel": "medium",
      "trendBias": "Range",
      "convictionScore": 35,
      "currentClose": 173.28,
      "entryPriceTarget": 173.14,
      "targetClose": 173.6694,
      "oneDayHitRate": 1.0,
      "oneDayMae": 0.0006599074796747964,
      "notes": "Bullish forecast with no current position. Plan an entry only if the next session confirms the move and keeps risk tight."
    }
  ],
  "riskReductions": [
    {
      "ticker": "SPCX",
      "portfolioAction": "SELL",
      "setupLabel": "Risk reduction",
      "predictedReturn": -0.009658,
      "basePredictedReturn": -0.009658,
      "adjustedPredictedReturn": -0.009658,
      "calibrationEnabled": false,
      "calibrationModelVersion": null,
      "calibrationStatus": "disabled",
      "calibrationReasons": [],
      "eventRisk": "low",
      "confidenceLabel": "medium",
      "trendBias": "Range",
      "convictionScore": 35,
      "currentClose": 160.42,
      "entryPriceTarget": 159.88,
      "targetClose": 158.8782,
      "oneDayHitRate": 1.0,
      "oneDayMae": 0.0006599074796747964,
      "notes": "Bearish forecast against an existing position. Trim or exit into strength if the next session lets you."
    },
    {
      "ticker": "ORCL",
      "portfolioAction": "SELL",
      "setupLabel": "Risk reduction",
      "predictedReturn": -0.005536,
      "basePredictedReturn": -0.005536,
      "adjustedPredictedReturn": -0.005536,
      "calibrationEnabled": false,
      "calibrationModelVersion": null,
      "calibrationStatus": "disabled",
      "calibrationReasons": [],
      "eventRisk": "moderate",
      "confidenceLabel": "medium",
      "trendBias": "Downtrend",
      "convictionScore": 35,
      "currentClose": 143.76,
      "entryPriceTarget": 143.48,
      "targetClose": 142.9663,
      "oneDayHitRate": 1.0,
      "oneDayMae": 0.0006599074796747964,
      "notes": "Bearish forecast against an existing position. Trim or exit into strength if the next session lets you."
    }
  ],
  "watchlist": [
    {
      "ticker": "SMCI",
      "portfolioAction": "HOLD",
      "setupLabel": "Watchlist only",
      "predictedReturn": -0.00605,
      "basePredictedReturn": -0.00605,
      "adjustedPredictedReturn": -0.00605,
      "calibrationEnabled": false,
      "calibrationModelVersion": null,
      "calibrationStatus": "disabled",
      "calibrationReasons": [],
      "eventRisk": "high",
      "confidenceLabel": "medium",
      "trendBias": "Downtrend",
      "convictionScore": 35,
      "currentClose": 27.19,
      "entryPriceTarget": 27.13,
      "targetClose": 27.026,
      "oneDayHitRate": 1.0,
      "oneDayMae": 0.0006599074796747964,
      "notes": "No position yet and the edge is still soft. Keep it on the board, but stay patient for a cleaner trigger."
    },
    {
      "ticker": "DELL",
      "portfolioAction": "HOLD",
      "setupLabel": "Existing position management",
      "predictedReturn": 0.004983,
      "basePredictedReturn": 0.004983,
      "adjustedPredictedReturn": 0.004983,
      "calibrationEnabled": false,
      "calibrationModelVersion": null,
      "calibrationStatus": "disabled",
      "calibrationReasons": [],
      "eventRisk": "low",
      "confidenceLabel": "medium",
      "trendBias": "Uptrend",
      "convictionScore": 35,
      "currentClose": 411.8,
      "entryPriceTarget": 411.08,
      "targetClose": 413.8571,
      "oneDayHitRate": 1.0,
      "oneDayMae": 0.0006599074796747964,
      "notes": "You already own shares here. Keep the position on, manage the risk, and do not force a fresh add."
    },
    {
      "ticker": "AVGO",
      "portfolioAction": "HOLD",
      "setupLabel": "Existing position management",
      "predictedReturn": 0.002107,
      "basePredictedReturn": 0.002107,
      "adjustedPredictedReturn": 0.002107,
      "calibrationEnabled": false,
      "calibrationModelVersion": null,
      "calibrationStatus": "disabled",
      "calibrationReasons": [],
      "eventRisk": "moderate",
      "confidenceLabel": "medium",
      "trendBias": "Range",
      "convictionScore": 35,
      "currentClose": 373.9,
      "entryPriceTarget": 373.62,
      "targetClose": 374.6885,
      "oneDayHitRate": 1.0,
      "oneDayMae": 0.0006599074796747964,
      "notes": "You already own shares here. Keep the position on, manage the risk, and do not force a fresh add."
    }
  ],
  "newsItems": [
    {
      "id": "4a1fd66b-a958-4cf8-828f-f209ac03ef15",
      "ticker": "AMD",
      "title": "Tech stocks on track for record annual inflows as investors pile into the AI trade",
      "summary": "The inflows into tech remains very impressive.",
      "source": "Yahoo Finance",
      "publishedAt": "2026-07-06T15:47:03Z",
      "url": "https://finance.yahoo.com/markets/article/tech-stocks-on-track-for-record-annual-inflows-as-investors-pile-into-the-ai-trade-154703501.html"
    },
    {
      "id": "66ed75ca-c0cd-39f6-b5c6-22481199c2ba",
      "ticker": "AMD",
      "title": "Update: US Equity Indexes Advance as Communication Services, Technology Top Sector Charts While Crude Oil Trades Steady",
      "summary": "(Updates with index/price moves, macroeconomic data, and company news from the first paragraph.)",
      "source": "MT Newswires",
      "publishedAt": "2026-07-06T21:18:09Z",
      "url": "https://finance.yahoo.com/markets/stocks/articles/us-equity-indexes-advance-communication-211809818.html"
    },
    {
      "id": "9ab775d5-f0da-36b2-856a-c26fdfa0cea9",
      "ticker": "VRT",
      "title": "What Vertiv Stock Was Saying About The AI Factory Build-Out",
      "summary": "Before the stock took off, management was dropping increasingly specific clues about its central role in the AI infrastructure boom.",
      "source": "Trefis",
      "publishedAt": "2026-07-06T20:15:51Z",
      "url": "https://finance.yahoo.com/technology/ai/articles/vertiv-stock-saying-ai-factory-201551009.html"
    },
    {
      "id": "5cacc556-aaae-3169-a9b7-3f37b427e892",
      "ticker": "VRT",
      "title": "Will Vertiv\u2019s New Malaysia AI Cooling Hub Reshape Vertiv Holdings Co's (VRT) Data Center Narrative?",
      "summary": "Vertiv Holdings Co recently opened a manufacturing facility in Johor, Malaysia, expanding its regional footprint to serve AI and high\u2011density computing infrastructure demand across Asia, with full operationalization targeted for 2027 and capabilities spanning end\u2011to\u2011end manufactu",
      "source": "Simply Wall St.",
      "publishedAt": "2026-07-06T20:12:36Z",
      "url": "https://finance.yahoo.com/technology/ai/articles/vertiv-malaysia-ai-cooling-hub-201236202.html"
    },
    {
      "id": "e30c34c9-dd07-3503-b8d9-954118a3134c",
      "ticker": "ANET",
      "title": "The Wide-Open Possibilities The Options Market Sees In Cisco Stock",
      "summary": "If you hold shares in this networking giant, you are already exposed to a notably large potential swing in its value over the next year.",
      "source": "Trefis",
      "publishedAt": "2026-07-06T18:16:10Z",
      "url": "https://finance.yahoo.com/markets/options/articles/wide-open-possibilities-options-market-181610548.html"
    },
    {
      "id": "2b5a88ff-bdc6-32d1-96ef-35fda15390c1",
      "ticker": "ANET",
      "title": "Can Cisco's AI Networking Momentum Lift CSCO Stock Higher?",
      "summary": "CSCO's networking business is gaining momentum as AI infrastructure demand, campus refresh projects and hyperscaler deployments fuel a broader growth cycle.",
      "source": "Zacks",
      "publishedAt": "2026-07-06T16:19:00Z",
      "url": "https://finance.yahoo.com/technology/ai/articles/ciscos-ai-networking-momentum-lift-161900761.html"
    },
    {
      "id": "b2ed2bbb-e304-3b4c-9ab0-642756aea04d",
      "ticker": "SPCX",
      "title": "Want to Own SpaceX Stock? Here Are 3 Things Investors Should Know Right Now",
      "summary": "As major indexes add SpaceX, you may already have a small amount of the space stock in your portfolio.",
      "source": "Motley Fool",
      "publishedAt": "2026-07-06T22:25:00Z",
      "url": "https://finance.yahoo.com/markets/stocks/articles/want-own-spacex-stock-3-222500717.html"
    },
    {
      "id": "3362db22-ae6b-3a01-be96-e9298b761694",
      "ticker": "SPCX",
      "title": "$2 Trillion By Year\u2019s End? A Wild First Half Look Back in ETFs",
      "summary": "It\u2019s been a wild ride in markets and ETFs so far this year, with the industry smashing through the $1 trillion mark in June and well on its way to $2 trillion by year\u2019s end. The ETF Zoo crew this week breaks down the hot trends in the first half, the winners that surprised us and",
      "source": "etf.com",
      "publishedAt": "2026-07-06T21:51:39Z",
      "url": "https://finance.yahoo.com/markets/options/articles/2-trillion-end-wild-first-215139508.html"
    }
  ]
}